clisk/__init__.py
clisk/_clisk.py
clisk/arguments.py
clisk/options.py
clisk-0.0.6.dist-info/METADATA
clisk-0.0.6.dist-info/WHEEL
clisk-0.0.6.dist-info/top_level.txt
clisk-0.0.6.dist-info/RECORD
